fastpunct/__init__.py
fastpunct/fastpunct.py
fastpunct-2.0.2.dist-info/LICENSE
fastpunct-2.0.2.dist-info/METADATA
fastpunct-2.0.2.dist-info/WHEEL
fastpunct-2.0.2.dist-info/top_level.txt
fastpunct-2.0.2.dist-info/RECORD
