Metadata-Version: 2.1
Name: fastpunct
Version: 2.0.2
Summary: Punctuation restoration and spell correction.
Home-page: https://github.com/notAI-tech/fastPunct
Author: Hari Krishna Sai Kodali
Author-email: kodalihari.619@gmail.com
License: MIT
Platform: UNKNOWN
Classifier: License :: OSI Approved :: MIT License
Classifier: Programming Language :: Python
Classifier: Programming Language :: Python :: 3
Classifier: Programming Language :: Python :: 3.6
Classifier: Programming Language :: Python :: Implementation :: CPython
Classifier: Programming Language :: Python :: Implementation :: PyPy
Requires-Python: >=3.6.0
Requires-Dist: transformers (>=4.0.0rc1)
Requires-Dist: pydload (>=1.0.9)
Requires-Dist: torch (>=1.5.0)
Requires-Dist: sentencepiece
